bnq_py_core/__init__.py
bnq_py_core/logger_record.py
bnq_py_core/nacos_conf.py
bnq_py_core/read_conf_from_ini.py
bnq_py_core/singleton.py
python_core_ai_bnq-0.0.2.dist-info/METADATA
python_core_ai_bnq-0.0.2.dist-info/WHEEL
python_core_ai_bnq-0.0.2.dist-info/top_level.txt
python_core_ai_bnq-0.0.2.dist-info/RECORD
